setup.py
typekev_mlnd_probability/Binomialdistribution.py
typekev_mlnd_probability/Gaussiandistribution.py
typekev_mlnd_probability/Generaldistribution.py
typekev_mlnd_probability/__init__.py
typekev_mlnd_probability.egg-info/PKG-INFO
typekev_mlnd_probability.egg-info/SOURCES.txt
typekev_mlnd_probability.egg-info/dependency_links.txt
typekev_mlnd_probability.egg-info/not-zip-safe
typekev_mlnd_probability.egg-info/top_level.txt