Metadata-Version: 1.0
Name: typekev-mlnd-probability
Version: 1.1
Summary: Gaussian and Binomial distributions
Home-page: UNKNOWN
Author: Kevin Gonzalez
Author-email: typekev@gmail.com
License: UNKNOWN
Platform: UNKNOWN
